CHANGELOG.txt
LICENCE.txt
MANIFEST.in
README.txt
setup.py
rppatil/__init__.py
rppatil.egg-info/PKG-INFO
rppatil.egg-info/SOURCES.txt
rppatil.egg-info/dependency_links.txt
rppatil.egg-info/top_level.txt