Metadata-Version: 1.1
Name: rppatil
Version: 0.0.2
Summary: reads and writes jsons
Home-page: UNKNOWN
Author: Rahul P Patil
Author-email: rahulpp891994@gmail.com
License: MIT
Keywords: read and write jsons
Platform: UNKNOWN
Classifier: Development Status :: 5 - Production/Stable
Classifier: Intended Audience :: Education
Classifier: Operating System :: POSIX :: Linux
Classifier: License :: OSI Approved :: MIT License
Classifier: Programming Language :: Python :: 3
